lg_rez-4.0.16.dist-info/licenses/LICENSE
lgrez/__init__.py
lgrez/__main__.py
lgrez/bot.py
lgrez/commands.py
lgrez/commons.py
lgrez/config.py
lgrez/server_structure.json
lgrez/bdd/__init__.py
lgrez/bdd/base.py
lgrez/bdd/enums.py
lgrez/bdd/model_actions.py
lgrez/bdd/model_ia.py
lgrez/bdd/model_jeu.py
lgrez/bdd/model_joueurs.py
lgrez/blocs/__init__.py
lgrez/blocs/console.py
lgrez/blocs/env.py
lgrez/blocs/gsheets.py
lgrez/blocs/journey.py
lgrez/blocs/realshell.py
lgrez/blocs/structure.py
lgrez/blocs/tools.py
lgrez/features/__init__.py
lgrez/features/actions_publiques.py
lgrez/features/annexe.py
lgrez/features/chans.py
lgrez/features/communication.py
lgrez/features/gestion_actions.py
lgrez/features/gestion_ia.py
lgrez/features/informations.py
lgrez/features/inscription.py
lgrez/features/open_close.py
lgrez/features/special.py
lgrez/features/sync.py
lgrez/features/taches.py
lgrez/features/voter_agir.py
lg_rez-4.0.16.dist-info/METADATA
lg_rez-4.0.16.dist-info/WHEEL
lg_rez-4.0.16.dist-info/top_level.txt
lg_rez-4.0.16.dist-info/RECORD
