Metadata-Version: 2.4
Name: lg-rez
Version: 4.0.16
Summary: Discord bot for organizing Werewolf RP games ESPCI-style
Home-page: https://github.com/GRI-ESPCI/lg-rez
Author: Loïc Simon, Tom Lacoma
Author-email: loic.simon@espci.org, tom.lacoma@espci.org
Classifier: Development Status :: 5 - Production/Stable
Classifier: Framework :: AsyncIO
Classifier: Intended Audience :: Developers
Classifier: Natural Language :: French
Classifier: Programming Language :: Python :: 3.10
Classifier: License :: OSI Approved :: MIT License
Classifier: Operating System :: OS Independent
Classifier: Topic :: Games/Entertainment :: Role-Playing
Classifier: Topic :: Internet
Requires-Python: >=3.10
License-File: LICENSE
Requires-Dist: wheel==0.37.1
Requires-Dist: aioconsole==0.5.1
Requires-Dist: aiohttp==3.8.3
Requires-Dist: aiosignal==1.2.0
Requires-Dist: akinator[async]==1.0.3
Requires-Dist: async-timeout==4.0.2
Requires-Dist: asyncode==1.0.0
Requires-Dist: attrs==22.1.0
Requires-Dist: cachetools==5.2.0
Requires-Dist: certifi==2022.9.24
Requires-Dist: chardet==5.0.0
Requires-Dist: charset-normalizer==2.1.1
Requires-Dist: contourpy==1.0.5
Requires-Dist: cycler==0.11.0
Requires-Dist: discord.py==2.1.0
Requires-Dist: discord==2.1.0
Requires-Dist: fonttools==4.37.4
Requires-Dist: frozenlist==1.3.1
Requires-Dist: google-api-core==2.10.2
Requires-Dist: google-api-python-client==2.64.0
Requires-Dist: google-auth-httplib2==0.1.0
Requires-Dist: google-auth-oauthlib==0.5.3
Requires-Dist: google-auth==2.12.0
Requires-Dist: googleapis-common-protos==1.56.4
Requires-Dist: greenlet==1.1.3.post0
Requires-Dist: gspread-asyncio==1.7.1
Requires-Dist: gspread==5.5.0
Requires-Dist: httplib2==0.20.4
Requires-Dist: idna==3.4
Requires-Dist: kiwisolver==1.4.4
Requires-Dist: matplotlib==3.6.1
Requires-Dist: multidict==6.0.2
Requires-Dist: numpy==1.23.4
Requires-Dist: oauth2client==4.1.3
Requires-Dist: oauthlib==3.2.1
Requires-Dist: packaging==21.3
Requires-Dist: Pillow==9.2.0
Requires-Dist: protobuf==4.21.7
Requires-Dist: psycopg2==2.9.4
Requires-Dist: pyasn1-modules==0.2.8
Requires-Dist: pyasn1==0.4.8
Requires-Dist: pyparsing==3.0.9
Requires-Dist: python-dateutil==2.8.2
Requires-Dist: python-dotenv==0.21.0
Requires-Dist: pytz==2022.4
Requires-Dist: readycheck==1.0.1
Requires-Dist: requests-oauthlib==1.3.1
Requires-Dist: requests==2.28.1
Requires-Dist: rsa==4.9
Requires-Dist: six==1.16.0
Requires-Dist: SQLAlchemy==1.4.41
Requires-Dist: typing_extensions==4.4.0
Requires-Dist: Unidecode==1.3.6
Requires-Dist: uritemplate==4.1.1
Requires-Dist: urllib3==1.26.12
Requires-Dist: yarl==1.8.1
Dynamic: author
Dynamic: author-email
Dynamic: classifier
Dynamic: description
Dynamic: description-content-type
Dynamic: home-page
Dynamic: license-file
Dynamic: requires-dist
Dynamic: requires-python
Dynamic: summary
